{
  "draft": false,
  "categories": [],
  "experience": "learn",
  "type": "article",
  "title": "Using the tax tool when your Form 1095-A is missing some information",
  "meta-title": "Using the tax tool when your Form 1095-A is missing some information",
  "meta-description": "Using the tax tool when your Form 1095-A is missing some information",
  "title-short": null,
  "bite": "Using the tax tool when your Form 1095-A is missing some information",
  "lang": "en",
  "layout": null,
  "seo-keywords": "",
  "state": "",
  "page_name": "Using the tax tool when your Form 1095-A is missing some information",
  "page_type": "single-page",
  "page_topic": "Using the tax tool when your Form 1095-A is missing some information",
  "page_lifecycle": "education",
  "page_audience": "individuals",
  "slug": "need-to-use-tool",
  "ext": ".md",
  "tags": [],
  "excerpt": "<p>Most people get their Form 1095-A in their Marketplace account. A few may see this message:</p>",
  "content": "<p>Most people get their Form 1095-A in their Marketplace account. A few may see this message:</p><p><strong>This form is missing some information. Use a tax tool along with this 1095-A.</strong></p><p>If you see this message in your account, this means you need to get more information before you can find out the amount of the premium tax credit (also called a subsidy or savings) you qualify for based on your final income.</p><ul class=\"ds-c-list\"><li>You'll need correct and complete information about the <a href=\"/node/40251\" data-entity-type=\"node\" data-entity-uuid=\"94a82b95-37a1-405c-97b9-177afbaa46c0\" data-entity-substitution=\"canonical\" data-entity-id=\"40251\" data-entity-bundle=\"brief\" title=\"Second lowest cost Silver plan (term tooltip)\">second lowest cost Silver plan (SLCSP)</a> that applied to you in 2025. It\u2019s not necessarily the plan that you were enrolled in.</li><li>When you use the tax tool, we\u2019ll ask you some questions and provide your SLCSP premiums.</li><li>You\u2019ll use your SLCSP premiums from the tool, along with other information on your Form 1095-A, to complete IRS Form 8962, Premium Tax Credit, and determine the amount of the premium tax credit you qualify for.</li></ul><p><a class=\"ds-c-button ds-c-button--success\" href=\"/tax-tool/\" data-entity-bundle data-entity-id data-internal-href target>Start tax tool</a></p>",
  "url": "/help/need-to-use-tool",
  "insurance-status": ""
}